flask_attachment/.DS_Store
flask_attachment/Manager.py
flask_attachment/__init__.py
flask_attachment/__pycache__/__init__.cpython-37.pyc
flask_attachment/data/FileInfo.py
flask_attachment/data/Operation.py
flask_attachment/data/__init__.py
flask_attachment/data/__pycache__/FileInfo.cpython-37.pyc
flask_attachment/data/__pycache__/__init__.cpython-37.pyc
flask_attachment/handler/BaseHandler.py
flask_attachment/handler/BinaryzationHandler.py
flask_attachment/handler/CropSquareHandler.py
flask_attachment/handler/MoveHandler.py
flask_attachment/handler/RemoveHandler.py
flask_attachment/handler/ResizeHandler.py
flask_attachment/handler/__init__.py
flask_attachment/helper/__init__.py
flask_attachment/helper/__pycache__/__init__.cpython-37.pyc
flask_attachment/helper/snowflake/SnowflakeHelper.py
flask_attachment/helper/snowflake/__init__.py
flask_attachment/helper/snowflake/__pycache__/SnowflakeHelper.cpython-37.pyc
flask_attachment/helper/snowflake/__pycache__/__init__.cpython-37.pyc
flask_attachment/utils/__init__.py
flask_attachment/utils/__pycache__/__init__.cpython-37.pyc
flask_attachment/utils/decorator/Singleton.py
flask_attachment/utils/decorator/__init__.py
flask_attachment/utils/decorator/__pycache__/Singleton.cpython-37.pyc
flask_attachment/utils/decorator/__pycache__/__init__.cpython-37.pyc
flask_attachment/utils/file/__init__.py
flask_attachment/utils/file/file.py
flask_attachment/utils/file/image.py
flask_attachment/utils/file/__pycache__/__init__.cpython-37.pyc
flask_attachment/utils/file/__pycache__/file.cpython-37.pyc
flask_attachment/utils/file/__pycache__/image.cpython-37.pyc
flask_attachment/utils/snowflake/Snowflake.py
flask_attachment/utils/snowflake/__init__.py
flask_attachment/utils/snowflake/__pycache__/Snowflake.cpython-37.pyc
flask_attachment/utils/snowflake/__pycache__/__init__.cpython-37.pyc
Flask_Attachment_New-1.0.1.dist-info/METADATA
Flask_Attachment_New-1.0.1.dist-info/WHEEL
Flask_Attachment_New-1.0.1.dist-info/top_level.txt
Flask_Attachment_New-1.0.1.dist-info/RECORD
