Metadata-Version: 2.1
Name: Flask-Attachment-New
Version: 1.0.1
Summary: attachment file
Home-page: http://iotwonderful.com
Author: zhangchi, lisichen
Author-email: UNKNOWN
License: BSD
Platform: any
Classifier: Environment :: Web Environment
Classifier: Intended Audience :: Developers
Classifier: License :: OSI Approved :: BSD License
Classifier: Operating System :: OS Independent
Classifier: Programming Language :: Python
Classifier: Topic :: Internet :: WWW/HTTP :: Dynamic Content
Classifier: Topic :: Software Development :: Libraries :: Python Modules
Requires-Dist: Flask
Requires-Dist: Pillow
